isqdeployer/__init__.py
isqdeployer/circuit.py
isqdeployer/circuitBlock.py
isqdeployer/intermediateRepresentation.py
isqdeployer/isQmaker.py
isqdeployer/porter.py
isqdeployer/ansatz/__init__.py
isqdeployer/ansatz/abcAnsatz.py
isqdeployer/backend/__init__.py
isqdeployer/backend/abcBackend.py
isqdeployer/backend/abcInteractiveBackend.py
isqdeployer/backend/cxy_backend.py
isqdeployer/backend/guodun_backend.py
isqdeployer/backend/numpy_simulator.py
isqdeployer/backend/simLibDrive.py
isqdeployer/backend/tmp_noisySimulator.py
isqdeployer/circuitDeployer/__init__.py
isqdeployer/circuitDeployer/abcDeployer.py
isqdeployer/circuitDeployer/gateDeployer.py
isqdeployer/circuitDeployer/particleConservingDeployer.py
isqdeployer/circuitDeployer/pauliHamiltonian.py
isqdeployer/isQ/bitOper.isq
isqdeployer/isQ/extension.isq
isqdeployer/isQ/math.isq
isqdeployer/isQ/particleConserving.isq
isqdeployer/isQ/Physics/Hubbard.isq
isqdeployer/isQ/Physics/Spin.isq
isqdeployer/isQ/Physics/errorcode.isq
isqdeployer/isQ/Physics/interaction.isq
isqdeployer/isQ/Physics/pauliHam.isq
isqdeployer/utils/__init__.py
isqdeployer/utils/cacheStore.py
isqdeployer/utils/fasthash.py
isqdeployer/utils/pauliHamiltonian.py
isqdeployer/utils/uni.py
isqdeployer-0.0.51.dist-info/METADATA
isqdeployer-0.0.51.dist-info/WHEEL
isqdeployer-0.0.51.dist-info/top_level.txt
isqdeployer-0.0.51.dist-info/RECORD
